usb_plug_notification_darwin/IOKit.bridgesupport
usb_plug_notification_darwin/__init__.py
usb_plug_notification_darwin/main.py
usb_plug_notification_darwin-0.2.0.dist-info/METADATA
usb_plug_notification_darwin-0.2.0.dist-info/WHEEL
usb_plug_notification_darwin-0.2.0.dist-info/entry_points.txt
usb_plug_notification_darwin-0.2.0.dist-info/RECORD
